datafed/CLI.py
datafed/CommandLib.py
datafed/Config.py
datafed/Connection.py
datafed/MessageLib.py
datafed/SDMS_Anon_pb2.py
datafed/SDMS_Auth_pb2.py
datafed/SDMS_pb2.py
datafed/VERSION.py
datafed/VersionUtils.py
datafed/Version_pb2.py
datafed/__init__.py
datafed_test-3.1.0rc16781.dist-info/METADATA
datafed_test-3.1.0rc16781.dist-info/WHEEL
datafed_test-3.1.0rc16781.dist-info/entry_points.txt
datafed_test-3.1.0rc16781.dist-info/top_level.txt
datafed_test-3.1.0rc16781.dist-info/RECORD
